django_form_generator/__init__.py
django_form_generator/__version__.py
django_form_generator/admin.py
django_form_generator/apps.py
django_form_generator/const.py
django_form_generator/fields.py
django_form_generator/forms.py
django_form_generator/managers.py
django_form_generator/models.py
django_form_generator/settings.py
django_form_generator/tests.py
django_form_generator/urls.py
django_form_generator/views.py
django_form_generator/api/serializers.py
django_form_generator/api/urls.py
django_form_generator/api/views.py
django_form_generator/common/__init__.py
django_form_generator/common/admins.py
django_form_generator/common/helpers.py
django_form_generator/common/models.py
django_form_generator/common/utils.py
django_form_generator/common/views.py
django_form_generator/docs/images/apiManagerCreateUser.png
django_form_generator/docs/images/apiManagerGetUser.png
django_form_generator/docs/images/ckEditor.png
django_form_generator/migrations/0001_initial.py
django_form_generator/migrations/0002_field_read_only_field_write_only.py
django_form_generator/migrations/0003_remove_field_error_message_remove_field_file_size_and_more.py
django_form_generator/migrations/0004_fieldoptionthrough_remove_fieldvaluethrough_field_and_more.py
django_form_generator/migrations/0005_alter_field_genre_alter_fieldvalidator_validator.py
django_form_generator/migrations/0006_alter_fieldvalidator_unique_together_and_more.py
django_form_generator/migrations/__init__.py
django_form_generator/static/htmx.min.js
django_form_generator/templates/django_form_generator/base.html
django_form_generator/templates/django_form_generator/form.html
django_form_generator/templates/django_form_generator/form_response.html
django_form_generator/templates/django_form_generator/fields/dynamic_fields.html
django_form_generator/templates/django_form_generator/fields/inline_fields.html
django_form_generator/templates/django_form_generator/fields/inorder_fields.html
django_form_generator-0.0.55.dist-info/LICENSE
django_form_generator-0.0.55.dist-info/METADATA
django_form_generator-0.0.55.dist-info/WHEEL
django_form_generator-0.0.55.dist-info/top_level.txt
django_form_generator-0.0.55.dist-info/RECORD
