Metadata-Version: 2.1
Name: django-form-generator
Version: 0.0.55
Summary: An app to create any form in django admin panel.
Home-page: https://github.com/m3h-D/Form-Generator/tree/main
Author: Mahdi Asadnejad
Maintainer: Mahdi Asadnejad
License: MIT
Keywords: django form generator form_generator django_form_generator
Classifier: Environment :: Web Environment
Classifier: Framework :: Django :: 4.1
Classifier: Intended Audience :: Developers
Classifier: License :: OSI Approved :: MIT License
Classifier: Operating System :: OS Independent
Classifier: Programming Language :: Python :: 3.10
Classifier: Topic :: Internet :: WWW/HTTP
Requires-Python: >=3.10
License-File: LICENSE
Requires-Dist: Django (>=4.0)
Requires-Dist: requests (>=2.28.1)
Requires-Dist: django-htmx (>=1.12.2)
Requires-Dist: crispy-bootstrap5 (>=0.6)
Requires-Dist: django-recaptcha (>=3.0.0)
Requires-Dist: django-crispy-forms (>=1.14.0)
Requires-Dist: django-tempus-dominus (>=5.1.2.0)
Requires-Dist: drf-recaptcha (>=2.0.0)
Requires-Dist: djangorestframework (>=3.0.0)
